README.rst
setup.cfg
setup.py
curve_shortening_flow/__init__.py
curve_shortening_flow/derivative.py
curve_shortening_flow/evaluation.py
curve_shortening_flow/get_vertices.py
curve_shortening_flow/hmi.py
curve_shortening_flow/iterator.py
curve_shortening_flow/time_step.py
curve_shortening_flow.egg-info/PKG-INFO
curve_shortening_flow.egg-info/SOURCES.txt
curve_shortening_flow.egg-info/dependency_links.txt
curve_shortening_flow.egg-info/not-zip-safe
curve_shortening_flow.egg-info/requires.txt
curve_shortening_flow.egg-info/top_level.txt
curve_shortening_flow/animation/__init__.py
curve_shortening_flow/animation/animate.py