Metadata-Version: 1.0
Name: curve-shortening-flow
Version: 2.1
Summary: minimization of curavature in 2d
Home-page: https://gitlab.gwdg.de/kevin.luedemann/curve_shortening_flow.git
Author: Alexander Kurz, Kevin Luedemann
Author-email: alexander.kurz@stud.uni-goettingen.de, kevin.luedemann@stud.uni-goettingen.de
License: BSD-3
Platform: UNKNOWN
